studfile/__init__.py
studfile/main.py
studfile/parser.py
studfile/runner.py
studfile-0.1.2.dist-info/METADATA
studfile-0.1.2.dist-info/WHEEL
studfile-0.1.2.dist-info/entry_points.txt
studfile-0.1.2.dist-info/RECORD
